jsonx.py
jsonx-2020.10.0.dist-info/METADATA
jsonx-2020.10.0.dist-info/WHEEL
jsonx-2020.10.0.dist-info/top_level.txt
jsonx-2020.10.0.dist-info/RECORD
