Metadata-Version: 1.0
Name: jsonx
Version: 2020.10.0
Summary: JSONx, an XML representation of the JSON data model
Home-page: UNKNOWN
Author: Wouter Bolsterlee
Author-email: uws@xs4all.nl
License: UNKNOWN
Platform: UNKNOWN
